{
 "creation": "2019-12-30 13:36:24.331861",
 "doctype": "DocType",
 "editable_grid": 1,
 "engine": "InnoDB",
 "field_order": [
  "duty",
  "employee",
  "employee_name"
 ],
 "fields": [
  {
   "fieldname": "duty",
   "fieldtype": "Select",
   "in_list_view": 1,
   "label": "Duty",
   "options": "Supervisor\nMachine Operator\nMachine Helper\nLeakage Checker\nBox Packing"
  },
  {
   "fieldname": "employee",
   "fieldtype": "Link",
   "in_list_view": 1,
   "label": "Employee",
   "options": "Employee"
  },
  {
   "fetch_from": "employee.employee_name",
   "fieldname": "employee_name",
   "fieldtype": "Data",
   "label": "Employee Name"
  }
 ],
 "istable": 1,
 "modified": "2020-04-08 21:24:03.939551",
 "modified_by": "Administrator",
 "module": "PNI Customization",
 "name": "Employee Team Table",
 "owner": "Administrator",
 "permissions": [],
 "quick_entry": 1,
 "sort_field": "modified",
 "sort_order": "DESC",
 "track_changes": 1
}